Workbook

Sheet Build Plan
A1: Yap Fantasy - Build Plan to Kickoff
A2: Set Status on each row. Milestones tab counts update automatically.
A4: ID | B4: Phase | C4: Task | D4: Start | E4: Due | F4: Days | G4: Status | H4: Depends On | I4: Cut Order | J4: Notes
A5: 1 | B5: P0 Foundations | C5: Enroll Apple Developer Program ($99/yr) | D5: 46252 | E5: 46252 | F5: =E5-D5+1 -> 1 | G5: Not started | I5: Blocker | J5: Takes 24-48h. Nothing reaches a device until it clears.
A6: 2 | B6: P0 Foundations | C6: Subscribe balldontlie NFL GOAT ($39.99/mo); store key in Supabase secrets | D6: 46252 | E6: 46252 | F6: =E6-D6+1 -> 1 | G6: Not started | I6: Blocker | J6: 600 req/min. Key lives in Edge Functions only.
A7: 3 | B7: P0 Foundations | C7: Scaffold Expo Router app (TypeScript, expo-router, reanimated, nativewind) | D7: 46252 | E7: 46253 | F7: =E7-D7+1 -> 2 | G7: Not started | I7: Blocker | J7: Verify web AND iOS simulator both render on day one.
A8: 4 | B8: P0 Foundations | C8: Supabase project + CLI linked + migrations workflow | D8: 46253 | E8: 46253 | F8: =E8-D8+1 -> 1 | G8: Not started | H8: 2 | I8: Blocker | J8: Every schema change is a migration file. No dashboard clicks.
A9: 5 | B9: P0 Foundations | C9: Auth: Supabase email magic link | D9: 46253 | E9: 46254 | F9: =E9-D9+1 -> 2 | G9: Not started | H9: 3, 4 | I9: Blocker | J9: Magic link only = no Sign in with Apple needed. Google/X login would force it.
A10: 6 | B10: P0 Foundations | C10: App Store Connect app record + bundle ID + app icon | D10: 46254 | E10: 46254 | F10: =E10-D10+1 -> 1 | G10: Not started | H10: 1 | I10: Blocker | J10: Placeholder icon is fine, it just cannot be empty.
A11: 7 | B11: P0 Foundations | C11: First EAS dev build installed on your own iPhone | D11: 46254 | E11: 46255 | F11: =E11-D11+1 -> 2 | G11: Not started | H11: 3, 6 | I11: Blocker | J11: Signing/provisioning eats 2-3 days. Lose them now, not in September.
A12: 8 | B12: P0 Foundations | C12: Deploy web build to Vercel/Cloudflare + auto-deploy on push | D12: 46255 | E12: 46255 | F12: =E12-D12+1 -> 1 | G12: Not started | H12: 3 | I12: Blocker | J12: expo export --platform web -> static site. Your kickoff insurance.
A13: 9 | B13: P1 Data spine | C13: Schema v1 migration: profiles, players, teams, cards, card_instances, packs, gems_ledger, stat_lines | D13: 46254 | E13: 46256 | F13: =E13-D13+1 -> 3 | G13: Not started | H13: 4 | I13: Blocker | J13: card = player template. card_instance = the copy a user owns. Never merge.
A14: 10 | B14: P1 Data spine | C14: RLS policies + a test that proves user A cannot read user B's roster | D14: 46256 | E14: 46256 | F14: =E14-D14+1 -> 1 | G14: Not started | H14: 9 | I14: Blocker | J14: Write the failing test first. Your testers are engineers.
A15: 11 | B15: P1 Data spine | C15: StatsProvider interface + balldontlie adapter | D15: 46255 | E15: 46256 | F15: =E15-D15+1 -> 2 | G15: Not started | H15: 2 | I15: Blocker | J15: Nothing above this layer imports balldontlie types.
A16: 12 | B16: P1 Data spine | C16: Nightly players/teams sync Edge Function + cron | D16: 46257 | E16: 46257 | F16: =E16-D16+1 -> 1 | G16: Not started | H16: 11 | I16: 4 | J16: Team rosters only exist from the 2025 season onward.
A17: 13 | B17: P1 Data spine | C17: Weekly DFS salary snapshot -> rarity band assignment | D17: 46257 | E17: 46258 | F17: =E17-D17+1 -> 2 | G17: Not started | H17: 11, 12 | I17: 3 | J17: Persist every snapshot - slates disappear. Fall back to 2025 season stats.
A18: 14 | B18: P1 Data spine | C18: Stat ingestion: games -> game_ids -> /stats paginated -> raw stat_lines | D18: 46258 | E18: 46259 | F18: =E18-D18+1 -> 2 | G18: Not started | H18: 11 | I18: Blocker | J18: /stats has no week param and no fantasy points. Resolve /games -> ids first.
A19: 15 | B19: P1 Data spine | C19: Scoring engine: pure fn(stat_line, rules_version) -> points, with unit tests | D19: 46259 | E19: 46259 | F19: =E19-D19+1 -> 1 | G19: Not started | H19: 14 | I19: Blocker | J19: Store raw stats AND points. Scoring will change; recompute, never re-ingest.
... A39: 35 | B39: P5 Kickoff | C39: Week 1 opener - monitor ingestion live | D39: 46274 | E39: 46274 | F39: =E39-D39+1 -> 1 | G39: Not started | H39: 33 | I39: - | J39: Wednesday opener (Thursday game is in Australia). Watch the first sweep.

Sheet Milestones
A1: Milestones & Progress
A3: PROGRESS
A4: Total tasks | B4: =COUNTA('Build Plan'!A5:A39) -> 35
A5: Done | B5: =COUNTIF('Build Plan'!G5:G39,"Done") -> 0
A6: In progress | B6: =COUNTIF('Build Plan'!G5:G39,"In progress") -> 0
A7: Blocked | B7: =COUNTIF('Build Plan'!G5:G39,"Blocked") -> 0
A8: Not started | B8: =COUNTIF('Build Plan'!G5:G39,"Not started") -> 35
A9: Cut | B9: =COUNTIF('Build Plan'!G5:G39,"Cut") -> 0
A10: % complete | B10: =IFERROR(COUNTIF('Build Plan'!G5:G39,"Done")/COUNTA('Build Plan'!A5:A39),0) -> 0
A11: Blockers left | B11: =COUNTIFS('Build Plan'!I5:I39,"Blocker",'Build Plan'!G5:G39,"<>Done") -> 23
A12: Days to kickoff | B12: =DATE(2026,9,9)-TODAY() -> 22
A14: MILESTONES
A15: Date | B15: Milestone | C15: Why it matters | D15: Hit?
A16: 46255 | B16: Dev build on your phone + web deployed | C16: If this slips, everything slips. | D16: No
A17: 46259 | B17: Ingestion produces real fantasy points from real games | C17: The moment the app has a reason to exist. | D17: No
A18: 46263 | B18: Preseason validation complete | C18: HARD DEADLINE - last live data before Week 1. | D18: No
A19: 46265 | B19: Core loop playable end to end | C19: Open pack -> collection -> lineup -> lock. | D19: No
A20: 46266 | B20: Internal TestFlight in friends' hands | C20: No App Review needed. Real users, 8 days early. | D20: No
A21: 46267 | B21: Feature freeze + external TestFlight submitted | C21: Budgets one rejection round. | D21: No
A22: 46271 | B22: Friends dry run complete | C22: Simulated Week 0, full loop. | D22: No
A23: 46274 | B23: KICKOFF - NFL Week 1 opener | C23: Wednesday. 22 days from Aug 18. | D23: No

Sheet Deferred
A1: Explicitly NOT in the Sept 9 beta
A2: A contract with yourself. Anything that creeps back in costs the kickoff date.
A4: Feature | B4: Target | C4: Why it waits
A5: Sets / Museum | B5: Ship Week 3 | C5: Nobody can complete a set in Week 1 anyway. Buys three weeks.
A6: Card selling | B6: Late Sept | C6: Blocked on the set-reward decision. Gem sinks balance together.
A7: Tier ranking (museum duplicates as fuel) | B7: Late Sept | C7: Makes duplicate pulls valuable. Not day-one important.
A8: Free agent market | B8: October | C8: Adds an economy AND a moderation surface.
A9: Discord bot (read-only) | B9: October | C9: Lock + pull results to a channel, OAuth-linked. A weekend once core is stable.
A10: In-app purchases | B10: Not in beta | C10: Earned gems only. Tests fun before monetization.
A11: Profile beyond name + avatar | B11: Late Sept | C11: No bios, stats pages, or follower graph.
A12: Real player art | B12: When you generate it | C12: Position glyph + rarity palette. Layout does not change when art lands.

Sheet Risks
A1: Risks & Mitigations
A3: Risk | B3: Likelihood | C3: Impact if it lands | D3: Mitigation
A4: Apple Developer enrollment stalls | B4: High | C4: Nothing reaches a phone | D4: Started Aug 18. Web build ships regardless.
A5: Beta App Review rejects the external build | B5: Medium | C5: Friends cannot install by Sept 9 | D5: Web live Aug 21 + internal TestFlight covers 100 friends without review.
A6: Preseason data window closes ~Aug 29 | B6: High | C6: Ingestion untested against live data until kickoff | D6: Task 16 is hard, not soft. If it slips, replay 2025 stat lines.
A7: No DFS slates in preseason / bye weeks | B7: Medium | C7: Rarity assignment has gaps | D7: Fallback tier from 2025 season stats. Persist every snapshot.
A8: Scoring rules change mid-beta | B8: Certain | C8: Rescoring pain | D8: Raw stat_lines stored apart from points, rules versioned. Recompute is a query.
A9: balldontlie /stats has no week param | B9: Certain | C9: Naive ingestion is wrong | D9: Resolve week -> game_ids via /games. Handled in task 14.
A10: Undocumented API shape drift | B10: Low | C10: Ingestion breaks silently | D10: StatsProvider (task 11) makes a swap one file. Alert on zero-row sweeps.
A11: Scope creep from your own good ideas | B11: Certain | C11: Miss kickoff | D11: The Deferred tab is the contract. Sept 2 freeze enforces it.

Sheet Decisions
A1: Locked decisions & open questions
A3: Decision | B3: Status | C3: Rationale / what unblocks it
A4: Expo Router universal app (one codebase -> iOS + web) | B4: LOCKED | C4: One codebase, file-based routing, native on iOS and React Native Web in the browser. A separate Next.js app is the trap on a first universal build.
A5: Supabase for auth, Postgres, Edge Functions, cron | B5: LOCKED | C5: Already wired up. RLS does the multi-tenant work for you.
A6: balldontlie NFL GOAT, $39.99/mo, 600 req/min | B6: LOCKED | C6: A supported contract, not Sleeper's undocumented endpoints. Adds DFS salaries, injuries, play-by-play.
A7: Rarity derived from DFS salary bands | B7: PROPOSED | C7: Salary is a weekly market valuation of every player: rarity with zero manual curation, and gated set slots become a query.
A8: Server-authoritative RNG, gems, and lineup locks | B8: LOCKED | C8: Testers are your engineer friends. Assume Charles Proxy.
A9: No player photos, logos, or jerseys | B9: LOCKED | C9: Names + stats have solid fantasy precedent. Likenesses and marks do not.
A10: Zero IAP in the beta | B10: LOCKED | C10: Sidesteps loot-box odds disclosure, StoreKit, and the 30%.
A11: Set reward mechanic (gated slots vs points-scaled payout vs duplicate fuel) | B11: OPEN | C11: Blocks card schema and faucet rates, both painful to change once people own collections. Decide before task 9 ships Aug 22.
A12: Fantasy scoring rules (PPR? bonuses? tier multipliers?) | B12: OPEN | C12: Needed by task 15. Low stakes - raw stats are stored, rescoring is a query.
